{
  "aor": 0.004560822784810127,
  "aqi": 0.008737758670886076,
  "bids_meta": {
    "acq_id": "D2S3",
    "dataset": "<unset>",
    "modality": "bold",
    "run_id": 1,
    "session_id": "7",
    "subject_id": "5153",
    "task_id": "Sem"
  },
  "dummy_trs": 0,
  "dvars_nstd": 55.304272427070096,
  "dvars_std": 1.1729102436942676,
  "dvars_vstd": 1.048698030382166,
  "efc": 0.43336710053107197,
  "fber": 2503.228515625,
  "fd_mean": 0.31707851488465394,
  "fd_num": 121,
  "fd_perc": 76.58227848101266,
  "fwhm_avg": 3.493261740832929,
  "fwhm_x": 3.1967,
  "fwhm_y": 3.550175,
  "fwhm_z": 3.732910222498788,
  "gcor": 0.0175896,
  "gsr_x": -0.022105157375335693,
  "gsr_y": 0.024885904043912888,
  "provenance": {
    "md5sum": "ca27cd8ab3e09ea8c1c34bd8a638bde0",
    "settings": {
      "fd_thres": 0.2,
      "hmc_fsl": false,
      "testing": false
    },
    "software": "mriqc",
    "version": "0.15.2",
    "webapi_port": null,
    "webapi_url": "https://mriqc.nimh.nih.gov/api/v1"
  },
  "size_t": 158,
  "size_x": 128,
  "size_y": 128,
  "size_z": 56,
  "snr": 1.9004276188934472,
  "spacing_tr": 1.25,
  "spacing_x": 2.0,
  "spacing_y": 2.0,
  "spacing_z": 1.9999998807907104,
  "summary_bg_k": 84.00432617506291,
  "summary_bg_mad": 4.419655515141242,
  "summary_bg_mean": 23.47110939025879,
  "summary_bg_median": 13.044303894042969,
  "summary_bg_n": 637702.0,
  "summary_bg_p05": 9.632911682128906,
  "summary_bg_p95": 52.80379867553711,
  "summary_bg_stdv": 46.763065338134766,
  "summary_fg_k": 1.6059917939054582,
  "summary_fg_mad": 311.3090026709383,
  "summary_fg_mean": 762.4585571289062,
  "summary_fg_median": 687.0570068359375,
  "summary_fg_n": 180075.0,
  "summary_fg_p05": 332.04241638183595,
  "summary_fg_p95": 1491.1006835937496,
  "summary_fg_stdv": 361.5265808105469,
  "tsnr": 27.681132157333195
}