{
  "aor": 0.004461376146788991,
  "aqi": 0.012634864174311929,
  "bids_meta": {
    "acq_id": "D1S12",
    "dataset": "<unset>",
    "modality": "bold",
    "run_id": 1,
    "session_id": "9",
    "subject_id": "5157",
    "task_id": "Gram"
  },
  "dummy_trs": 0,
  "dvars_nstd": 67.15659768225812,
  "dvars_std": 1.1111825233179724,
  "dvars_vstd": 1.0256707899539168,
  "efc": 0.4408437450645523,
  "fber": 2324.747802734375,
  "fd_mean": 0.43273374870569253,
  "fd_num": 166,
  "fd_perc": 76.14678899082568,
  "fwhm_avg": 3.226138333333333,
  "fwhm_x": 2.896085,
  "fwhm_y": 3.298105,
  "fwhm_z": 3.484225,
  "gcor": 0.0117162,
  "gsr_x": -0.0036960477009415627,
  "gsr_y": 0.021717997267842293,
  "provenance": {
    "md5sum": "c27133805b7633b757018f05033d90fd",
    "settings": {
      "fd_thres": 0.2,
      "hmc_fsl": false,
      "testing": false
    },
    "software": "mriqc",
    "version": "0.15.2",
    "webapi_port": null,
    "webapi_url": "https://mriqc.nimh.nih.gov/api/v1"
  },
  "size_t": 218,
  "size_x": 128,
  "size_y": 128,
  "size_z": 56,
  "snr": 2.1097227399139884,
  "spacing_tr": 1.25,
  "spacing_x": 2.0,
  "spacing_y": 2.0,
  "spacing_z": 2.0,
  "summary_bg_k": 75.90487061411794,
  "summary_bg_mad": 4.685840029812439,
  "summary_bg_mean": 24.45625877380371,
  "summary_bg_median": 12.013760566711426,
  "summary_bg_n": 644155.0,
  "summary_bg_p05": 8.073393821716309,
  "summary_bg_p95": 74.53807296752898,
  "summary_bg_stdv": 51.791500091552734,
  "summary_fg_k": 0.6802149771635846,
  "summary_fg_mad": 263.53589250111906,
  "summary_fg_mean": 670.6932373046875,
  "summary_fg_median": 608.1467895507812,
  "summary_fg_n": 172592.0,
  "summary_fg_p05": 317.5025177001953,
  "summary_fg_p95": 1230.0770202636716,
  "summary_fg_stdv": 288.2582702636719,
  "tsnr": 22.28331748628989
}