{
  "aor": 0.0019920253164556964,
  "aqi": 0.007516222658227847,
  "bids_meta": {
    "acq_id": "D1S3",
    "dataset": "<unset>",
    "modality": "bold",
    "run_id": 1,
    "session_id": "7",
    "subject_id": "5446",
    "task_id": "Sem"
  },
  "dummy_trs": 0,
  "dvars_nstd": 59.268495498789804,
  "dvars_std": 1.1631837659235666,
  "dvars_vstd": 1.0322846880254777,
  "efc": 0.4175116863493717,
  "fber": 2587.486083984375,
  "fd_mean": 0.19339578197279153,
  "fd_num": 53,
  "fd_perc": 33.54430379746835,
  "fwhm_avg": 3.378528333333333,
  "fwhm_x": 3.06607,
  "fwhm_y": 3.40111,
  "fwhm_z": 3.668405,
  "gcor": 0.00478002,
  "gsr_x": -0.01703551597893238,
  "gsr_y": 0.024282041937112808,
  "provenance": {
    "md5sum": "ffdeb8948214746e2fcec7d6ce405daa",
    "settings": {
      "fd_thres": 0.2,
      "hmc_fsl": false,
      "testing": false
    },
    "software": "mriqc",
    "version": "0.15.2",
    "webapi_port": null,
    "webapi_url": "https://mriqc.nimh.nih.gov/api/v1"
  },
  "size_t": 158,
  "size_x": 128,
  "size_y": 128,
  "size_z": 56,
  "snr": 1.8938750427593083,
  "spacing_tr": 1.25,
  "spacing_x": 2.0,
  "spacing_y": 2.0,
  "spacing_z": 2.0,
  "summary_bg_k": 61.77310740257907,
  "summary_bg_mad": 3.884793745443143,
  "summary_bg_mean": 23.373567581176758,
  "summary_bg_median": 11.48734188079834,
  "summary_bg_n": 656761.0,
  "summary_bg_p05": 8.234177589416504,
  "summary_bg_p95": 64.14556884765625,
  "summary_bg_stdv": 50.504791259765625,
  "summary_fg_k": 1.4743809721108256,
  "summary_fg_mad": 270.16208558278856,
  "summary_fg_mean": 694.6098022460938,
  "summary_fg_median": 617.5759887695312,
  "summary_fg_n": 159479.0,
  "summary_fg_p05": 315.4538177490235,
  "summary_fg_p95": 1354.776647949219,
  "summary_fg_stdv": 326.0901794433594,
  "tsnr": 27.892783617717214
}