{
  "aor": 0.0013966981132075473,
  "aqi": 0.009111908160377357,
  "bids_meta": {
    "acq_id": "D2S8",
    "dataset": "<unset>",
    "modality": "bold",
    "run_id": 2,
    "session_id": "9",
    "subject_id": "5125",
    "task_id": "Plaus"
  },
  "dummy_trs": 0,
  "dvars_nstd": 48.04841713175354,
  "dvars_std": 1.0827810410426542,
  "dvars_vstd": 0.9870432461611373,
  "efc": 0.4266852409589495,
  "fber": 3026.125,
  "fd_mean": 0.21229956544942205,
  "fd_num": 121,
  "fd_perc": 57.075471698113205,
  "fwhm_avg": 3.133941666666667,
  "fwhm_x": 2.811085,
  "fwhm_y": 3.460585,
  "fwhm_z": 3.130155,
  "gcor": 0.0186071,
  "gsr_x": -0.016729392111301422,
  "gsr_y": 0.01826964132487774,
  "provenance": {
    "md5sum": "7efaa06ecdc97b14647ab1f506b3a4a8",
    "settings": {
      "fd_thres": 0.2,
      "hmc_fsl": false,
      "testing": false
    },
    "software": "mriqc",
    "version": "0.15.2",
    "webapi_port": null,
    "webapi_url": "https://mriqc.nimh.nih.gov/api/v1"
  },
  "size_t": 212,
  "size_x": 128,
  "size_y": 128,
  "size_z": 56,
  "snr": 2.3737590522608363,
  "spacing_tr": 1.25,
  "spacing_x": 2.0,
  "spacing_y": 2.0,
  "spacing_z": 2.0,
  "summary_bg_k": 99.1029252947797,
  "summary_bg_mad": 3.377815885305389,
  "summary_bg_mean": 23.482460021972656,
  "summary_bg_median": 12.037735939025879,
  "summary_bg_n": 658410.0,
  "summary_bg_p05": 9.358490943908691,
  "summary_bg_p95": 62.896698570250805,
  "summary_bg_stdv": 50.80867385864258,
  "summary_fg_k": 0.05470342674298312,
  "summary_fg_mad": 301.66756370774874,
  "summary_fg_mean": 739.0322265625,
  "summary_fg_median": 702.3396606445312,
  "summary_fg_n": 161103.0,
  "summary_fg_p05": 327.30235290527344,
  "summary_fg_p95": 1273.5278442382812,
  "summary_fg_stdv": 295.8756408691406,
  "tsnr": 29.01161028095521
}