{
  "aor": 0.0032536075949367083,
  "aqi": 0.008213597025316457,
  "bids_meta": {
    "acq_id": "D2S2",
    "dataset": "<unset>",
    "modality": "bold",
    "run_id": 1,
    "session_id": "7",
    "subject_id": "5104",
    "task_id": "Sem"
  },
  "dummy_trs": 0,
  "dvars_nstd": 49.817259332993636,
  "dvars_std": 1.0889950948407645,
  "dvars_vstd": 1.0218623353503187,
  "efc": 0.4347698740817149,
  "fber": 2260.505126953125,
  "fd_mean": 0.2286915555150238,
  "fd_num": 79,
  "fd_perc": 50.0,
  "fwhm_avg": 3.3279583333333336,
  "fwhm_x": 3.066305,
  "fwhm_y": 3.42008,
  "fwhm_z": 3.49749,
  "gcor": 0.0167046,
  "gsr_x": -0.01027129590511322,
  "gsr_y": 0.014592710882425308,
  "provenance": {
    "md5sum": "2eacd3cc34dc940c39a99dcded5b3f31",
    "settings": {
      "fd_thres": 0.2,
      "hmc_fsl": false,
      "testing": false
    },
    "software": "mriqc",
    "version": "0.15.2",
    "webapi_port": null,
    "webapi_url": "https://mriqc.nimh.nih.gov/api/v1"
  },
  "size_t": 158,
  "size_x": 128,
  "size_y": 128,
  "size_z": 56,
  "snr": 2.013123670751349,
  "spacing_tr": 1.25,
  "spacing_x": 2.0,
  "spacing_y": 2.0,
  "spacing_z": 2.0,
  "summary_bg_k": 53.06495782778937,
  "summary_bg_mad": 4.823148595565915,
  "summary_bg_mean": 26.948566436767578,
  "summary_bg_median": 13.531645774841309,
  "summary_bg_n": 647828.0,
  "summary_bg_p05": 9.848101615905762,
  "summary_bg_p95": 84.1265869140625,
  "summary_bg_stdv": 53.471588134765625,
  "summary_fg_k": 1.2823742114901338,
  "summary_fg_mad": 311.9000889558064,
  "summary_fg_mean": 741.74267578125,
  "summary_fg_median": 679.7088623046875,
  "summary_fg_n": 170295.0,
  "summary_fg_p05": 318.08038024902345,
  "summary_fg_p95": 1388.6392822265625,
  "summary_fg_stdv": 337.6379089355469,
  "tsnr": 28.06626863917336
}