{
  "aor": 0.008692522935779816,
  "aqi": 0.00846124481651376,
  "bids_meta": {
    "acq_id": "D2S2",
    "dataset": "<unset>",
    "modality": "bold",
    "run_id": 1,
    "session_id": "7",
    "subject_id": "5044",
    "task_id": "Gram"
  },
  "dummy_trs": 0,
  "dvars_nstd": 59.61619817497695,
  "dvars_std": 1.2667872433640563,
  "dvars_vstd": 1.0951438140092167,
  "efc": 0.44981791654591874,
  "fber": 1526.0667724609375,
  "fd_mean": 0.22065314646654696,
  "fd_num": 62,
  "fd_perc": 28.440366972477065,
  "fwhm_avg": 3.234995,
  "fwhm_x": 2.90851,
  "fwhm_y": 3.305595,
  "fwhm_z": 3.49088,
  "gcor": 0.0562017,
  "gsr_x": -0.016156692057847977,
  "gsr_y": 0.01972406543791294,
  "provenance": {
    "md5sum": "eb729144c94661f3b97ab54cb5ee6f32",
    "settings": {
      "fd_thres": 0.2,
      "hmc_fsl": false,
      "testing": false
    },
    "software": "mriqc",
    "version": "0.15.2",
    "webapi_port": null,
    "webapi_url": "https://mriqc.nimh.nih.gov/api/v1"
  },
  "size_t": 218,
  "size_x": 128,
  "size_y": 128,
  "size_z": 56,
  "snr": 2.0991122373156528,
  "spacing_tr": 1.25,
  "spacing_x": 2.0,
  "spacing_y": 2.0,
  "spacing_z": 2.0,
  "summary_bg_k": 85.68770311680326,
  "summary_bg_mad": 3.0536168331781535,
  "summary_bg_mean": 25.1673526763916,
  "summary_bg_median": 16.357797622680664,
  "summary_bg_n": 632075.0,
  "summary_bg_p05": 13.908256530761719,
  "summary_bg_p95": 50.93256607055632,
  "summary_bg_stdv": 40.97154235839844,
  "summary_fg_k": 1.86868225186939,
  "summary_fg_mad": 284.4079708768021,
  "summary_fg_mean": 734.5354614257812,
  "summary_fg_median": 675.8508911132812,
  "summary_fg_n": 184108.0,
  "summary_fg_p05": 336.7814178466797,
  "summary_fg_p95": 1354.8391662597655,
  "summary_fg_stdv": 321.968994140625,
  "tsnr": 25.70827730325982
}