{
  "aor": 0.004395316455696202,
  "aqi": 0.011794407025316455,
  "bids_meta": {
    "acq_id": "D1S5",
    "dataset": "<unset>",
    "modality": "bold",
    "run_id": 1,
    "session_id": "7",
    "subject_id": "5474",
    "task_id": "Phon"
  },
  "dummy_trs": 0,
  "dvars_nstd": 61.18841253872614,
  "dvars_std": 1.0534396212738852,
  "dvars_vstd": 1.0193709375159237,
  "efc": 0.4361173995700155,
  "fber": 2398.281494140625,
  "fd_mean": 0.4484652299218194,
  "fd_num": 127,
  "fd_perc": 80.37974683544304,
  "fwhm_avg": 3.4742583333333332,
  "fwhm_x": 3.134985,
  "fwhm_y": 3.518915,
  "fwhm_z": 3.768875,
  "gcor": 0.00977143,
  "gsr_x": -0.014364294707775116,
  "gsr_y": 0.018113475292921066,
  "provenance": {
    "md5sum": "ab49787b16d9ed1600c1b8770b32b8e8",
    "settings": {
      "fd_thres": 0.2,
      "hmc_fsl": false,
      "testing": false
    },
    "software": "mriqc",
    "version": "0.15.2",
    "webapi_port": null,
    "webapi_url": "https://mriqc.nimh.nih.gov/api/v1"
  },
  "size_t": 158,
  "size_x": 128,
  "size_y": 128,
  "size_z": 56,
  "snr": 1.8107619806758772,
  "spacing_tr": 1.25,
  "spacing_x": 2.0,
  "spacing_y": 2.0,
  "spacing_z": 2.0,
  "summary_bg_k": 63.726269978366204,
  "summary_bg_mad": 5.207876134299754,
  "summary_bg_mean": 23.90263557434082,
  "summary_bg_median": 12.651899337768555,
  "summary_bg_n": 633070.0,
  "summary_bg_p05": 8.47468376159668,
  "summary_bg_p95": 60.73418045043945,
  "summary_bg_stdv": 48.07537841796875,
  "summary_fg_k": 1.6550428903948857,
  "summary_fg_mad": 296.14042734268446,
  "summary_fg_mean": 743.8628540039062,
  "summary_fg_median": 654.3797607421875,
  "summary_fg_n": 183846.0,
  "summary_fg_p05": 329.8734130859375,
  "summary_fg_p95": 1473.8291625976562,
  "summary_fg_stdv": 361.3826599121094,
  "tsnr": 22.43033792747883
}