{
  "aor": 0.0032982278481012654,
  "aqi": 0.008130264810126582,
  "bids_meta": {
    "acq_id": "D1S4",
    "dataset": "<unset>",
    "modality": "bold",
    "run_id": 1,
    "session_id": "5",
    "subject_id": "5085",
    "task_id": "Phon"
  },
  "dummy_trs": 0,
  "dvars_nstd": 64.4525643365605,
  "dvars_std": 1.1809921128025478,
  "dvars_vstd": 1.0748080111464962,
  "efc": 0.44688219491064607,
  "fber": 1315.3858642578125,
  "fd_mean": 0.26271174431456257,
  "fd_num": 87,
  "fd_perc": 55.063291139240505,
  "fwhm_avg": 3.2793233333333336,
  "fwhm_x": 2.99728,
  "fwhm_y": 3.37559,
  "fwhm_z": 3.4651,
  "gcor": 0.00711475,
  "gsr_x": -0.013741451315581799,
  "gsr_y": 0.020633716136217117,
  "provenance": {
    "md5sum": "9f56d74bcb258b7288c362bf2970985f",
    "settings": {
      "fd_thres": 0.2,
      "hmc_fsl": false,
      "testing": false
    },
    "software": "mriqc",
    "version": "0.15.2",
    "webapi_port": null,
    "webapi_url": "https://mriqc.nimh.nih.gov/api/v1"
  },
  "size_t": 158,
  "size_x": 128,
  "size_y": 128,
  "size_z": 56,
  "snr": 2.0130826897461276,
  "spacing_tr": 1.0,
  "spacing_x": 2.0,
  "spacing_y": 2.0,
  "spacing_z": 2.0,
  "summary_bg_k": 99.4241675779238,
  "summary_bg_mad": 39.22328505015917,
  "summary_bg_mean": 307.2652282714844,
  "summary_bg_median": 192.87342834472656,
  "summary_bg_n": 639877.0,
  "summary_bg_p05": 161.13291931152344,
  "summary_bg_p95": 696.5480957031227,
  "summary_bg_stdv": 480.818115234375,
  "summary_fg_k": 1.4603971303748713,
  "summary_fg_mad": 3177.6103704717957,
  "summary_fg_mean": 8289.9638671875,
  "summary_fg_median": 7436.66455078125,
  "summary_fg_n": 176423.0,
  "summary_fg_p05": 4002.819799804687,
  "summary_fg_p95": 15542.9833984375,
  "summary_fg_stdv": 3694.156982421875,
  "tsnr": 27.05674734141212
}