{
  "aor": 0.01796398734177215,
  "aqi": 0.024368234936708862,
  "bids_meta": {
    "acq_id": "D1S8",
    "dataset": "<unset>",
    "modality": "bold",
    "run_id": 2,
    "session_id": "7",
    "subject_id": "5317",
    "task_id": "Phon"
  },
  "dummy_trs": 0,
  "dvars_nstd": 96.45491955980886,
  "dvars_std": 1.251344300573249,
  "dvars_vstd": 1.1265173689171977,
  "efc": 0.4325220428033084,
  "fber": 1317.7528076171875,
  "fd_mean": 0.7746714233998553,
  "fd_num": 134,
  "fd_perc": 84.81012658227849,
  "fwhm_avg": 3.517948333333333,
  "fwhm_x": 3.223905,
  "fwhm_y": 3.54527,
  "fwhm_z": 3.78467,
  "gcor": 0.0982183,
  "gsr_x": -0.016007646918296814,
  "gsr_y": 0.015334418043494225,
  "provenance": {
    "md5sum": "3ed90fa2962fd4910a9197bef3b3a0d9",
    "settings": {
      "fd_thres": 0.2,
      "hmc_fsl": false,
      "testing": false
    },
    "software": "mriqc",
    "version": "0.15.2",
    "webapi_port": null,
    "webapi_url": "https://mriqc.nimh.nih.gov/api/v1"
  },
  "size_t": 158,
  "size_x": 128,
  "size_y": 128,
  "size_z": 56,
  "snr": 1.8641713863577294,
  "spacing_tr": 1.25,
  "spacing_x": 2.0,
  "spacing_y": 2.0,
  "spacing_z": 2.0,
  "summary_bg_k": 60.67855754873969,
  "summary_bg_mad": 3.809725923001184,
  "summary_bg_mean": 28.846874237060547,
  "summary_bg_median": 16.962026596069336,
  "summary_bg_n": 656090.0,
  "summary_bg_p05": 14.044303894042969,
  "summary_bg_p95": 71.47816848754839,
  "summary_bg_stdv": 49.081363677978516,
  "summary_fg_k": 1.1521474327605699,
  "summary_fg_mad": 285.09597287065577,
  "summary_fg_mean": 734.0172729492188,
  "summary_fg_median": 652.91455078125,
  "summary_fg_n": 162770.0,
  "summary_fg_p05": 320.13577728271486,
  "summary_fg_p95": 1461.2279052734375,
  "summary_fg_stdv": 350.2427673339844,
  "tsnr": 15.86536033579614
}