{
  "aor": 0.005676075949367089,
  "aqi": 0.00979655911392405,
  "bids_meta": {
    "acq_id": "D1S3",
    "dataset": "<unset>",
    "modality": "bold",
    "run_id": 2,
    "session_id": "9",
    "subject_id": "5389",
    "task_id": "Phon"
  },
  "dummy_trs": 0,
  "dvars_nstd": 67.10130215299363,
  "dvars_std": 1.2613058198089173,
  "dvars_vstd": 1.0674458919108283,
  "efc": 0.434877585525838,
  "fber": 2519.18603515625,
  "fd_mean": 0.2193336079850424,
  "fd_num": 64,
  "fd_perc": 40.50632911392405,
  "fwhm_avg": 3.2874616666666667,
  "fwhm_x": 3.00945,
  "fwhm_y": 3.38018,
  "fwhm_z": 3.472755,
  "gcor": 0.00464764,
  "gsr_x": -0.019650287926197052,
  "gsr_y": 0.027760254219174385,
  "provenance": {
    "md5sum": "c1de5b636ee8d0c2aa0bd267c3b88a6e",
    "settings": {
      "fd_thres": 0.2,
      "hmc_fsl": false,
      "testing": false
    },
    "software": "mriqc",
    "version": "0.15.2",
    "webapi_port": null,
    "webapi_url": "https://mriqc.nimh.nih.gov/api/v1"
  },
  "size_t": 158,
  "size_x": 128,
  "size_y": 128,
  "size_z": 56,
  "snr": 1.9722542146044562,
  "spacing_tr": 1.25,
  "spacing_x": 2.0,
  "spacing_y": 2.0,
  "spacing_z": 2.0,
  "summary_bg_k": 104.78533634540851,
  "summary_bg_mad": 3.9786285234955914,
  "summary_bg_mean": 21.363338470458984,
  "summary_bg_median": 11.715189933776855,
  "summary_bg_n": 636418.0,
  "summary_bg_p05": 8.588607788085938,
  "summary_bg_p95": 49.677215576171875,
  "summary_bg_stdv": 44.32093811035156,
  "summary_fg_k": 1.704492994488838,
  "summary_fg_mad": 272.59239855778884,
  "summary_fg_mean": 689.844970703125,
  "summary_fg_median": 621.094970703125,
  "summary_fg_n": 178948.0,
  "summary_fg_p05": 322.78703155517576,
  "summary_fg_p95": 1302.6592407226558,
  "summary_fg_stdv": 314.9154052734375,
  "tsnr": 25.977083378238603
}