{
  "aor": 0.025552924528301886,
  "aqi": 0.027204109339622647,
  "bids_meta": {
    "acq_id": "D1S5",
    "dataset": "<unset>",
    "modality": "bold",
    "run_id": 2,
    "session_id": "7",
    "subject_id": "5580",
    "task_id": "Plaus"
  },
  "dummy_trs": 0,
  "dvars_nstd": 87.08910673639812,
  "dvars_std": 1.2025327402843602,
  "dvars_vstd": 1.171649015829384,
  "efc": 0.42822947628212227,
  "fber": 2568.901123046875,
  "fd_mean": 1.095795152455944,
  "fd_num": 150,
  "fd_perc": 70.75471698113208,
  "fwhm_avg": 3.2602516666666665,
  "fwhm_x": 2.949855,
  "fwhm_y": 3.437,
  "fwhm_z": 3.3939,
  "gcor": 0.0590763,
  "gsr_x": -0.01429188996553421,
  "gsr_y": 0.02053973078727722,
  "provenance": {
    "md5sum": "b94e17e8cc1cb23b038adcfce752aaee",
    "settings": {
      "fd_thres": 0.2,
      "hmc_fsl": false,
      "testing": false
    },
    "software": "mriqc",
    "version": "0.15.2",
    "webapi_port": null,
    "webapi_url": "https://mriqc.nimh.nih.gov/api/v1"
  },
  "size_t": 212,
  "size_x": 128,
  "size_y": 128,
  "size_z": 56,
  "snr": 2.3872498805056126,
  "spacing_tr": 1.25,
  "spacing_x": 2.0,
  "spacing_y": 2.0,
  "spacing_z": 2.0,
  "summary_bg_k": 62.25506704470956,
  "summary_bg_mad": 4.244998261641886,
  "summary_bg_mean": 23.921632766723633,
  "summary_bg_median": 11.636792182922363,
  "summary_bg_n": 663088.0,
  "summary_bg_p05": 8.051886558532715,
  "summary_bg_p95": 77.20755004882812,
  "summary_bg_stdv": 47.90230178833008,
  "summary_fg_k": 0.4156662185006801,
  "summary_fg_mad": 249.4268293844969,
  "summary_fg_mean": 661.2116088867188,
  "summary_fg_median": 618.632080078125,
  "summary_fg_n": 154253.0,
  "summary_fg_p05": 320.7905700683594,
  "summary_fg_p95": 1152.95283203125,
  "summary_fg_stdv": 259.13922119140625,
  "tsnr": 15.013166222954169
}