{
  "aor": 0.0024104245283018866,
  "aqi": 0.008695907216981132,
  "bids_meta": {
    "acq_id": "D1S5",
    "dataset": "<unset>",
    "modality": "bold",
    "run_id": 2,
    "session_id": "7",
    "subject_id": "5029",
    "task_id": "Plaus"
  },
  "dummy_trs": 0,
  "dvars_nstd": 53.26970462872038,
  "dvars_std": 1.1141267682938385,
  "dvars_vstd": 1.0124595744549765,
  "efc": 0.43327468626550064,
  "fber": 1513.210205078125,
  "fd_mean": 0.2664946902879446,
  "fd_num": 107,
  "fd_perc": 50.471698113207545,
  "fwhm_avg": 3.2442766666666665,
  "fwhm_x": 2.93142,
  "fwhm_y": 3.386,
  "fwhm_z": 3.41541,
  "gcor": 0.00577627,
  "gsr_x": -0.016790328547358513,
  "gsr_y": 0.012154068797826767,
  "provenance": {
    "md5sum": "8fd1fd37eaa3fcf22fb8464b259908ed",
    "settings": {
      "fd_thres": 0.2,
      "hmc_fsl": false,
      "testing": false
    },
    "software": "mriqc",
    "version": "0.15.2",
    "webapi_port": null,
    "webapi_url": "https://mriqc.nimh.nih.gov/api/v1"
  },
  "size_t": 212,
  "size_x": 128,
  "size_y": 128,
  "size_z": 56,
  "snr": 2.1263964798199004,
  "spacing_tr": 1.25,
  "spacing_x": 2.0,
  "spacing_y": 2.0,
  "spacing_z": 2.0,
  "summary_bg_k": 77.74792691815348,
  "summary_bg_mad": 2.5246200022182674,
  "summary_bg_mean": 25.04691505432129,
  "summary_bg_median": 15.820755004882812,
  "summary_bg_n": 656189.0,
  "summary_bg_p05": 13.867924690246582,
  "summary_bg_p95": 55.52641525268544,
  "summary_bg_stdv": 39.28765869140625,
  "summary_fg_k": 1.401909994309479,
  "summary_fg_mad": 269.8056420928781,
  "summary_fg_mean": 705.4155883789062,
  "summary_fg_median": 648.9953002929688,
  "summary_fg_n": 162089.0,
  "summary_fg_p05": 329.7952941894531,
  "summary_fg_p95": 1311.1764160156254,
  "summary_fg_stdv": 305.2080383300781,
  "tsnr": 27.606920827180147
}