{
  "aor": 0.0031132075471698114,
  "aqi": 0.012899637028301887,
  "bids_meta": {
    "acq_id": "D2S5",
    "dataset": "<unset>",
    "modality": "bold",
    "run_id": 1,
    "session_id": "7",
    "subject_id": "5457",
    "task_id": "Plaus"
  },
  "dummy_trs": 0,
  "dvars_nstd": 64.11862169924167,
  "dvars_std": 1.0669092936966824,
  "dvars_vstd": 1.0035276740758294,
  "efc": 0.41271743177820575,
  "fber": 2492.522705078125,
  "fd_mean": 0.4434322731710157,
  "fd_num": 166,
  "fd_perc": 78.30188679245283,
  "fwhm_avg": 3.308501666666667,
  "fwhm_x": 3.04181,
  "fwhm_y": 3.321265,
  "fwhm_z": 3.56243,
  "gcor": 0.00558769,
  "gsr_x": -0.015008998103439808,
  "gsr_y": 0.012357196770608425,
  "provenance": {
    "md5sum": "72b1974e0e9d555b72e5398cfc2b33fa",
    "settings": {
      "fd_thres": 0.2,
      "hmc_fsl": false,
      "testing": false
    },
    "software": "mriqc",
    "version": "0.15.2",
    "webapi_port": null,
    "webapi_url": "https://mriqc.nimh.nih.gov/api/v1"
  },
  "size_t": 212,
  "size_x": 128,
  "size_y": 128,
  "size_z": 56,
  "snr": 2.056850734365449,
  "spacing_tr": 1.25,
  "spacing_x": 2.0,
  "spacing_y": 2.0,
  "spacing_z": 2.0,
  "summary_bg_k": 81.67389138055631,
  "summary_bg_mad": 3.685525806389941,
  "summary_bg_mean": 21.165536880493164,
  "summary_bg_median": 11.235849380493164,
  "summary_bg_n": 669307.0,
  "summary_bg_p05": 8.301886558532715,
  "summary_bg_p95": 60.216983795166016,
  "summary_bg_stdv": 38.800743103027344,
  "summary_fg_k": 1.4542444306727909,
  "summary_fg_mad": 235.46096805075953,
  "summary_fg_mean": 657.5303955078125,
  "summary_fg_median": 591.103759765625,
  "summary_fg_n": 150149.0,
  "summary_fg_p05": 320.749072265625,
  "summary_fg_p95": 1236.355712890625,
  "summary_fg_stdv": 287.3819580078125,
  "tsnr": 22.474949325085618
}