{
  "aor": 0.011495063291139241,
  "aqi": 0.02355868006329114,
  "bids_meta": {
    "acq_id": "D1S3",
    "dataset": "<unset>",
    "modality": "bold",
    "run_id": 1,
    "session_id": "9",
    "subject_id": "5367",
    "task_id": "Sem"
  },
  "dummy_trs": 0,
  "dvars_nstd": 61.57622365286623,
  "dvars_std": 1.0642791335031845,
  "dvars_vstd": 0.9783053438216558,
  "efc": 0.42247086826793334,
  "fber": 2623.298095703125,
  "fd_mean": 0.2717439201431413,
  "fd_num": 59,
  "fd_perc": 37.34177215189873,
  "fwhm_avg": 3.19523,
  "fwhm_x": 2.91991,
  "fwhm_y": 3.42844,
  "fwhm_z": 3.23734,
  "gcor": 0.0716943,
  "gsr_x": -0.02096971869468689,
  "gsr_y": 0.01908765733242035,
  "provenance": {
    "md5sum": "b0a738fdf13ed26c1cc9e2a5d3062a8e",
    "settings": {
      "fd_thres": 0.2,
      "hmc_fsl": false,
      "testing": false
    },
    "software": "mriqc",
    "version": "0.15.2",
    "webapi_port": null,
    "webapi_url": "https://mriqc.nimh.nih.gov/api/v1"
  },
  "size_t": 158,
  "size_x": 128,
  "size_y": 128,
  "size_z": 56,
  "snr": 2.289056035955872,
  "spacing_tr": 1.25,
  "spacing_x": 2.0,
  "spacing_y": 2.0,
  "spacing_z": 2.0,
  "summary_bg_k": 52.119157819587336,
  "summary_bg_mad": 3.481300665018471,
  "summary_bg_mean": 24.500957489013672,
  "summary_bg_median": 12.196203231811523,
  "summary_bg_n": 665165.0,
  "summary_bg_p05": 9.36708927154541,
  "summary_bg_p95": 76.03164672851562,
  "summary_bg_stdv": 47.931983947753906,
  "summary_fg_k": 0.9974816303111376,
  "summary_fg_mad": 271.44757608971827,
  "summary_fg_mean": 703.8873901367188,
  "summary_fg_median": 662.1044311523438,
  "summary_fg_n": 152702.0,
  "summary_fg_p05": 322.9949478149414,
  "summary_fg_p95": 1254.377545166015,
  "summary_fg_stdv": 289.2468566894531,
  "tsnr": 20.991988450055942
}