{
  "aor": 0.0026117088607594935,
  "aqi": 0.007952646645569621,
  "bids_meta": {
    "acq_id": "D2S3",
    "dataset": "<unset>",
    "modality": "bold",
    "run_id": 1,
    "session_id": "5",
    "subject_id": "5123",
    "task_id": "Phon"
  },
  "dummy_trs": 0,
  "dvars_nstd": 69.25040416369427,
  "dvars_std": 1.2717095817834396,
  "dvars_vstd": 1.0352591905095538,
  "efc": 0.4214351156153107,
  "fber": 1481.8262939453125,
  "fd_mean": 0.25593406591461854,
  "fd_num": 101,
  "fd_perc": 63.924050632911396,
  "fwhm_avg": 3.4535716666666665,
  "fwhm_x": 3.19048,
  "fwhm_y": 3.53817,
  "fwhm_z": 3.632065,
  "gcor": 0.0137037,
  "gsr_x": -0.006643902976065874,
  "gsr_y": 0.008490236476063728,
  "provenance": {
    "md5sum": "38ef148fa1dd969b8786c2714f7d4cce",
    "settings": {
      "fd_thres": 0.2,
      "hmc_fsl": false,
      "testing": false
    },
    "software": "mriqc",
    "version": "0.15.2",
    "webapi_port": null,
    "webapi_url": "https://mriqc.nimh.nih.gov/api/v1"
  },
  "size_t": 158,
  "size_x": 128,
  "size_y": 128,
  "size_z": 56,
  "snr": 1.8508867712640138,
  "spacing_tr": 1.25,
  "spacing_x": 2.0,
  "spacing_y": 2.0,
  "spacing_z": 2.0,
  "summary_bg_k": 130.4465126390449,
  "summary_bg_mad": 2.383424571327051,
  "summary_bg_mean": 22.10063362121582,
  "summary_bg_median": 15.537975311279297,
  "summary_bg_n": 651946.0,
  "summary_bg_p05": 13.544303894042969,
  "summary_bg_p95": 41.34652042388916,
  "summary_bg_stdv": 30.929044723510742,
  "summary_fg_k": 1.250572872290351,
  "summary_fg_mad": 284.85666979650796,
  "summary_fg_mean": 719.3954467773438,
  "summary_fg_median": 633.8734130859375,
  "summary_fg_n": 165692.0,
  "summary_fg_p05": 321.56329345703125,
  "summary_fg_p95": 1409.4556884765625,
  "summary_fg_stdv": 342.4690856933594,
  "tsnr": 28.27957815420814
}