{
  "aor": 0.010202848101265823,
  "aqi": 0.008947517341772153,
  "bids_meta": {
    "acq_id": "D2S7",
    "dataset": "<unset>",
    "modality": "bold",
    "run_id": 1,
    "session_id": "5",
    "subject_id": "5045",
    "task_id": "Sem"
  },
  "dummy_trs": 0,
  "dvars_nstd": 57.17596736859872,
  "dvars_std": 1.225114842420382,
  "dvars_vstd": 1.4073309486624193,
  "efc": 0.4305952666291186,
  "fber": 1178.6033935546875,
  "fd_mean": 0.45251448647289894,
  "fd_num": 106,
  "fd_perc": 67.0886075949367,
  "fwhm_avg": 3.5659183333333337,
  "fwhm_x": 3.39394,
  "fwhm_y": 3.86529,
  "fwhm_z": 3.438525,
  "gcor": 0.019349,
  "gsr_x": -0.012957502156496048,
  "gsr_y": 0.020045127719640732,
  "provenance": {
    "md5sum": "5556458bd0cdf86c71bbb5d039a31f49",
    "settings": {
      "fd_thres": 0.2,
      "hmc_fsl": false,
      "testing": false
    },
    "software": "mriqc",
    "version": "0.15.2",
    "webapi_port": null,
    "webapi_url": "https://mriqc.nimh.nih.gov/api/v1"
  },
  "size_t": 158,
  "size_x": 128,
  "size_y": 128,
  "size_z": 56,
  "snr": 1.7363886857419966,
  "spacing_tr": 1.25,
  "spacing_x": 2.0,
  "spacing_y": 2.0,
  "spacing_z": 2.0,
  "summary_bg_k": 126.90986634455669,
  "summary_bg_mad": 57.56798769421199,
  "summary_bg_mean": 393.7906799316406,
  "summary_bg_median": 274.376953125,
  "summary_bg_n": 640680.0,
  "summary_bg_p05": 225.14890060424807,
  "summary_bg_p95": 848.6004180908194,
  "summary_bg_stdv": 474.35321044921875,
  "summary_fg_k": 2.4809983879814137,
  "summary_fg_mad": 5185.1348541372045,
  "summary_fg_mean": 11332.2958984375,
  "summary_fg_median": 10108.650390625,
  "summary_fg_n": 175478.0,
  "summary_fg_p05": 4441.369189453125,
  "summary_fg_p95": 22353.156835937498,
  "summary_fg_stdv": 5821.63525390625,
  "tsnr": 26.888818740844727
}