{
  "aor": 0.0028159633027522936,
  "aqi": 0.008241552706422019,
  "bids_meta": {
    "acq_id": "D1S13",
    "dataset": "<unset>",
    "modality": "bold",
    "run_id": 2,
    "session_id": "7",
    "subject_id": "5034",
    "task_id": "Gram"
  },
  "dummy_trs": 0,
  "dvars_nstd": 64.71330350917053,
  "dvars_std": 1.2938169391244239,
  "dvars_vstd": 1.0511221129032264,
  "efc": 0.44239618591311336,
  "fber": 1487.4495849609375,
  "fd_mean": 0.240901973341561,
  "fd_num": 93,
  "fd_perc": 42.6605504587156,
  "fwhm_avg": 3.418958333333333,
  "fwhm_x": 3.11812,
  "fwhm_y": 3.4108,
  "fwhm_z": 3.727955,
  "gcor": 0.0158087,
  "gsr_x": -0.01770733669400215,
  "gsr_y": 0.017454013228416443,
  "provenance": {
    "md5sum": "cc91e3ce3f7ebac20593bdb12bdfaa75",
    "settings": {
      "fd_thres": 0.2,
      "hmc_fsl": false,
      "testing": false
    },
    "software": "mriqc",
    "version": "0.15.2",
    "webapi_port": null,
    "webapi_url": "https://mriqc.nimh.nih.gov/api/v1"
  },
  "size_t": 218,
  "size_x": 128,
  "size_y": 128,
  "size_z": 56,
  "snr": 1.838201769935216,
  "spacing_tr": 1.25,
  "spacing_x": 2.0,
  "spacing_y": 2.0,
  "spacing_z": 2.0,
  "summary_bg_k": 72.97988055599416,
  "summary_bg_mad": 3.380059775801422,
  "summary_bg_mean": 26.853601455688477,
  "summary_bg_median": 16.7385311126709,
  "summary_bg_n": 634997.0,
  "summary_bg_p05": 14.050457954406738,
  "summary_bg_p95": 57.087154388427734,
  "summary_bg_stdv": 45.62283706665039,
  "summary_fg_k": 1.9808545590923483,
  "summary_fg_mad": 304.03204458350814,
  "summary_fg_mean": 763.0474243164062,
  "summary_fg_median": 679.5504150390625,
  "summary_fg_n": 182040.0,
  "summary_fg_p05": 331.6190322875977,
  "summary_fg_p95": 1506.5203735351558,
  "summary_fg_stdv": 369.68115234375,
  "tsnr": 28.495068716816604
}