{
  "aor": 0.0014712658227848101,
  "aqi": 0.009713542784810125,
  "bids_meta": {
    "acq_id": "D2S14",
    "dataset": "<unset>",
    "modality": "bold",
    "run_id": 2,
    "session_id": "7",
    "subject_id": "5344",
    "task_id": "Sem"
  },
  "dummy_trs": 0,
  "dvars_nstd": 58.458399220127355,
  "dvars_std": 1.1240697782165607,
  "dvars_vstd": 1.0090210242038222,
  "efc": 0.414818900246294,
  "fber": 2526.678466796875,
  "fd_mean": 0.18526732819126854,
  "fd_num": 41,
  "fd_perc": 25.949367088607595,
  "fwhm_avg": 3.3586283333333333,
  "fwhm_x": 3.030605,
  "fwhm_y": 3.335135,
  "fwhm_z": 3.710145,
  "gcor": 0.00622923,
  "gsr_x": -0.020062053576111794,
  "gsr_y": 0.014057779684662819,
  "provenance": {
    "md5sum": "68b7f2d1d378945a7c522ffd77b9ea1f",
    "settings": {
      "fd_thres": 0.2,
      "hmc_fsl": false,
      "testing": false
    },
    "software": "mriqc",
    "version": "0.15.2",
    "webapi_port": null,
    "webapi_url": "https://mriqc.nimh.nih.gov/api/v1"
  },
  "size_t": 158,
  "size_x": 128,
  "size_y": 128,
  "size_z": 56,
  "snr": 1.938250469465431,
  "spacing_tr": 1.25,
  "spacing_x": 2.0,
  "spacing_y": 2.0,
  "spacing_z": 2.0,
  "summary_bg_k": 86.93152853497178,
  "summary_bg_mad": 3.85664260506758,
  "summary_bg_mean": 22.76311683654785,
  "summary_bg_median": 11.550633430480957,
  "summary_bg_n": 663346.0,
  "summary_bg_p05": 8.493671417236328,
  "summary_bg_p95": 57.70253372192383,
  "summary_bg_stdv": 50.997379302978516,
  "summary_fg_k": 1.6876635091627596,
  "summary_fg_mad": 247.16297434290362,
  "summary_fg_mean": 686.1890258789062,
  "summary_fg_median": 610.5570068359375,
  "summary_fg_n": 155971.0,
  "summary_fg_p05": 326.7911376953125,
  "summary_fg_p95": 1341.3765869140625,
  "summary_fg_stdv": 315.003173828125,
  "tsnr": 27.421489550732076
}