{
  "aor": 0.012996697247706421,
  "aqi": 0.018908143119266054,
  "bids_meta": {
    "acq_id": "D1S7",
    "dataset": "<unset>",
    "modality": "bold",
    "run_id": 1,
    "session_id": "5",
    "subject_id": "5104",
    "task_id": "Gram"
  },
  "dummy_trs": 0,
  "dvars_nstd": 76.9592112529493,
  "dvars_std": 1.1214356041474647,
  "dvars_vstd": 1.080213520737327,
  "efc": 0.4447267036396626,
  "fber": 951.089111328125,
  "fd_mean": 0.3547401535010855,
  "fd_num": 95,
  "fd_perc": 43.57798165137615,
  "fwhm_avg": 3.1792666666666665,
  "fwhm_x": 2.928875,
  "fwhm_y": 3.340985,
  "fwhm_z": 3.26794,
  "gcor": 0.0520061,
  "gsr_x": -0.006088782101869583,
  "gsr_y": 0.008486051112413406,
  "provenance": {
    "md5sum": "4f035d11e64932dc6e2e764c66cabaa6",
    "settings": {
      "fd_thres": 0.2,
      "hmc_fsl": false,
      "testing": false
    },
    "software": "mriqc",
    "version": "0.15.2",
    "webapi_port": null,
    "webapi_url": "https://mriqc.nimh.nih.gov/api/v1"
  },
  "size_t": 218,
  "size_x": 128,
  "size_y": 128,
  "size_z": 56,
  "snr": 2.095779853326702,
  "spacing_tr": 1.25,
  "spacing_x": 2.0,
  "spacing_y": 2.0,
  "spacing_z": 2.0,
  "summary_bg_k": 118.9601052231809,
  "summary_bg_mad": 39.51339874110942,
  "summary_bg_mean": 269.7544250488281,
  "summary_bg_median": 194.8577880859375,
  "summary_bg_n": 649897.0,
  "summary_bg_p05": 162.8210906982422,
  "summary_bg_p95": 530.3632812499998,
  "summary_bg_stdv": 311.2408752441406,
  "summary_fg_k": 1.1753439139970485,
  "summary_fg_mad": 2719.261867625568,
  "summary_fg_mean": 7001.67626953125,
  "summary_fg_median": 6370.13720703125,
  "summary_fg_n": 168097.0,
  "summary_fg_p05": 3244.6375000000003,
  "summary_fg_p95": 12908.502734374999,
  "summary_fg_stdv": 3039.497802734375,
  "tsnr": 17.377101182413753
}