{
  "aor": 0.0005916509433962264,
  "aqi": 0.007421275283018867,
  "bids_meta": {
    "acq_id": "D2S6",
    "dataset": "<unset>",
    "modality": "bold",
    "run_id": 1,
    "session_id": "9",
    "subject_id": "5357",
    "task_id": "Plaus"
  },
  "dummy_trs": 0,
  "dvars_nstd": 55.790942675402796,
  "dvars_std": 1.07299350042654,
  "dvars_vstd": 1.0010624988151668,
  "efc": 0.41895801230399826,
  "fber": 2208.05078125,
  "fd_mean": 0.15619062588869706,
  "fd_num": 64,
  "fd_perc": 30.18867924528302,
  "fwhm_avg": 3.2947233333333332,
  "fwhm_x": 2.959025,
  "fwhm_y": 3.297595,
  "fwhm_z": 3.62755,
  "gcor": 0.00336397,
  "gsr_x": -0.018663235008716583,
  "gsr_y": 0.013343052938580513,
  "provenance": {
    "md5sum": "df31428e38975edfa1d5baa6c769b6c4",
    "settings": {
      "fd_thres": 0.2,
      "hmc_fsl": false,
      "testing": false
    },
    "software": "mriqc",
    "version": "0.15.2",
    "webapi_port": null,
    "webapi_url": "https://mriqc.nimh.nih.gov/api/v1"
  },
  "size_t": 212,
  "size_x": 128,
  "size_y": 128,
  "size_z": 56,
  "snr": 1.9679216826540413,
  "spacing_tr": 1.25,
  "spacing_x": 2.0,
  "spacing_y": 2.0,
  "spacing_z": 2.0,
  "summary_bg_k": 67.43236741397547,
  "summary_bg_mad": 4.0701628542657176,
  "summary_bg_mean": 23.40497589111328,
  "summary_bg_median": 11.773585319519043,
  "summary_bg_n": 666493.0,
  "summary_bg_p05": 8.466980934143066,
  "summary_bg_p95": 62.44528350830089,
  "summary_bg_stdv": 48.87446594238281,
  "summary_fg_k": 2.2029150670522437,
  "summary_fg_mad": 228.31377385379184,
  "summary_fg_mean": 652.6259155273438,
  "summary_fg_median": 583.660400390625,
  "summary_fg_n": 153381.0,
  "summary_fg_p05": 310.3537902832031,
  "summary_fg_p95": 1253.5849609375,
  "summary_fg_stdv": 296.58624267578125,
  "tsnr": 27.531991860596463
}