{
  "aor": 0.014511226415094341,
  "aqi": 0.00990734141509434,
  "bids_meta": {
    "acq_id": "D2S2",
    "dataset": "<unset>",
    "modality": "bold",
    "run_id": 1,
    "session_id": "7",
    "subject_id": "5476",
    "task_id": "Plaus"
  },
  "dummy_trs": 0,
  "dvars_nstd": 58.95811708241703,
  "dvars_std": 1.2956959951184839,
  "dvars_vstd": 1.1604429211848342,
  "efc": 0.4208817438941074,
  "fber": 2813.92724609375,
  "fd_mean": 0.4116070773638692,
  "fd_num": 116,
  "fd_perc": 54.716981132075475,
  "fwhm_avg": 3.354063333333333,
  "fwhm_x": 3.12957,
  "fwhm_y": 3.455465,
  "fwhm_z": 3.477155,
  "gcor": 0.0145581,
  "gsr_x": -0.02396678738296032,
  "gsr_y": 0.025962363928556442,
  "provenance": {
    "md5sum": "188663cfd0c04ceace311ef943faf597",
    "settings": {
      "fd_thres": 0.2,
      "hmc_fsl": false,
      "testing": false
    },
    "software": "mriqc",
    "version": "0.15.2",
    "webapi_port": null,
    "webapi_url": "https://mriqc.nimh.nih.gov/api/v1"
  },
  "size_t": 212,
  "size_x": 128,
  "size_y": 128,
  "size_z": 56,
  "snr": 2.0264827611604983,
  "spacing_tr": 1.25,
  "spacing_x": 2.0,
  "spacing_y": 2.0,
  "spacing_z": 2.0,
  "summary_bg_k": 69.78580374781313,
  "summary_bg_mad": 3.965261327056085,
  "summary_bg_mean": 24.540952682495117,
  "summary_bg_median": 12.485849380493164,
  "summary_bg_n": 657574.0,
  "summary_bg_p05": 8.94339656829834,
  "summary_bg_p95": 63.30188751220703,
  "summary_bg_stdv": 52.68278884887695,
  "summary_fg_k": 1.4870881792086816,
  "summary_fg_mad": 309.98975907395106,
  "summary_fg_mean": 764.3795166015625,
  "summary_fg_median": 701.0401000976562,
  "summary_fg_n": 161246.0,
  "summary_fg_p05": 332.73468017578125,
  "summary_fg_p95": 1440.7913208007812,
  "summary_fg_stdv": 345.9382629394531,
  "tsnr": 26.229483599308878
}